{"file":"superLotto.png","frames":{
"any_light":{"x":750,"y":435,"w":370,"h":54,"offX":0,"offY":0,"sourceW":370,"sourceH":54},
"ball_blue":{"x":305,"y":528,"w":150,"h":150,"offX":0,"offY":0,"sourceW":150,"sourceH":150},
"ball_golden":{"x":153,"y":528,"w":150,"h":150,"offX":0,"offY":0,"sourceW":150,"sourceH":150},
"ball_mega":{"x":1,"y":528,"w":150,"h":150,"offX":0,"offY":0,"sourceW":150,"sourceH":150},
"ball_silver":{"x":1871,"y":507,"w":150,"h":150,"offX":0,"offY":0,"sourceW":150,"sourceH":150},
"bar_any":{"x":729,"y":512,"w":726,"h":67,"offX":0,"offY":0,"sourceW":726,"sourceH":67},
"bar_sequence":{"x":1,"y":459,"w":726,"h":67,"offX":0,"offY":0,"sourceW":726,"sourceH":67},
"bg":{"x":1488,"y":157,"w":20,"h":20,"offX":0,"offY":0,"sourceW":20,"sourceH":20},
"bg_channle":{"x":1,"y":1,"w":1507,"h":154,"offX":0,"offY":0,"sourceW":1507,"sourceH":154},
"btn_down":{"x":1433,"y":581,"w":121,"h":67,"offX":0,"offY":0,"sourceW":121,"sourceH":67},
"btn_down_press":{"x":1310,"y":581,"w":121,"h":67,"offX":0,"offY":0,"sourceW":121,"sourceH":67},
"btn_orange":{"x":822,"y":581,"w":363,"h":49,"offX":0,"offY":0,"sourceW":363,"sourceH":49},
"btn_orange_press":{"x":457,"y":581,"w":363,"h":49,"offX":0,"offY":0,"sourceW":363,"sourceH":49},
"btn_up":{"x":1187,"y":581,"w":121,"h":67,"offX":0,"offY":0,"sourceW":121,"sourceH":67},
"btn_up_press":{"x":1886,"y":305,"w":121,"h":67,"offX":0,"offY":0,"sourceW":121,"sourceH":67},
"card_bg":{"x":1,"y":157,"w":747,"h":300,"offX":0,"offY":0,"sourceW":747,"sourceH":300},
"extra_blue":{"x":1886,"y":153,"w":150,"h":150,"offX":0,"offY":0,"sourceW":150,"sourceH":150},
"extra_golden":{"x":1886,"y":1,"w":150,"h":150,"offX":0,"offY":0,"sourceW":150,"sourceH":150},
"extra_silver":{"x":1719,"y":507,"w":150,"h":150,"offX":0,"offY":0,"sourceW":150,"sourceH":150},
"icon_golden":{"x":1430,"y":215,"w":56,"h":56,"offX":0,"offY":0,"sourceW":56,"sourceH":56},
"icon_silver":{"x":1430,"y":157,"w":56,"h":56,"offX":0,"offY":0,"sourceW":56,"sourceH":56},
"jackpot_bg":{"x":1567,"y":391,"w":432,"h":114,"offX":0,"offY":0,"sourceW":432,"sourceH":114},
"jackpot_lock":{"x":1126,"y":391,"w":439,"h":119,"offX":0,"offY":0,"sourceW":439,"sourceH":119},
"list_01":{"x":1510,"y":1,"w":374,"h":388,"offX":0,"offY":0,"sourceW":374,"sourceH":388},
"list_02":{"x":750,"y":157,"w":374,"h":276,"offX":0,"offY":0,"sourceW":374,"sourceH":276},
"mega_blue":{"x":1278,"y":157,"w":150,"h":150,"offX":0,"offY":0,"sourceW":150,"sourceH":150},
"mega_golden":{"x":1126,"y":157,"w":150,"h":150,"offX":0,"offY":0,"sourceW":150,"sourceH":150},
"mega_silver":{"x":1567,"y":507,"w":150,"h":150,"offX":0,"offY":0,"sourceW":150,"sourceH":150},
"sequence_light":{"x":1126,"y":309,"w":370,"h":54,"offX":0,"offY":0,"sourceW":370,"sourceH":54}}}