{"file":"halloween.png","frames":{
"G20":{"x":104,"y":585,"w":99,"h":52,"offX":0,"offY":0,"sourceW":99,"sourceH":52},
"G19":{"x":309,"y":559,"w":100,"h":52,"offX":0,"offY":0,"sourceW":100,"sourceH":52},
"G18":{"x":104,"y":517,"w":99,"h":66,"offX":0,"offY":0,"sourceW":99,"sourceH":66},
"G17":{"x":563,"y":339,"w":97,"h":62,"offX":0,"offY":0,"sourceW":97,"sourceH":62},
"G16":{"x":462,"y":397,"w":99,"h":60,"offX":0,"offY":0,"sourceW":99,"sourceH":60},
"G15":{"x":679,"y":451,"w":114,"h":52,"offX":0,"offY":0,"sourceW":114,"sourceH":52},
"G14":{"x":795,"y":454,"w":95,"h":52,"offX":0,"offY":0,"sourceW":95,"sourceH":52},
"G13":{"x":205,"y":602,"w":100,"h":52,"offX":0,"offY":0,"sourceW":100,"sourceH":52},
"G12":{"x":563,"y":403,"w":114,"h":52,"offX":0,"offY":0,"sourceW":114,"sourceH":52},
"G11":{"x":522,"y":85,"w":97,"h":64,"offX":0,"offY":0,"sourceW":97,"sourceH":64},
"G10":{"x":104,"y":639,"w":97,"h":52,"offX":0,"offY":0,"sourceW":97,"sourceH":52},
"G9":{"x":462,"y":333,"w":99,"h":62,"offX":0,"offY":0,"sourceW":99,"sourceH":62},
"G8":{"x":662,"y":339,"w":95,"h":62,"offX":0,"offY":0,"sourceW":95,"sourceH":62},
"G7":{"x":454,"y":459,"w":106,"h":52,"offX":0,"offY":0,"sourceW":106,"sourceH":52},
"G6":{"x":452,"y":513,"w":102,"h":52,"offX":0,"offY":0,"sourceW":102,"sourceH":52},
"G5":{"x":346,"y":451,"w":106,"h":52,"offX":0,"offY":0,"sourceW":106,"sourceH":52},
"G4":{"x":104,"y":449,"w":99,"h":66,"offX":0,"offY":0,"sourceW":99,"sourceH":66},
"G3":{"x":205,"y":548,"w":102,"h":52,"offX":0,"offY":0,"sourceW":102,"sourceH":52},
"G2":{"x":346,"y":505,"w":104,"h":52,"offX":0,"offY":0,"sourceW":104,"sourceH":52},
"G1":{"x":563,"y":457,"w":112,"h":52,"offX":0,"offY":0,"sourceW":112,"sourceH":52},
"20 Lines":{"x":644,"y":85,"w":160,"h":124,"offX":0,"offY":0,"sourceW":160,"sourceH":124},
"9":{"x":806,"y":85,"w":124,"h":123,"offX":0,"offY":0,"sourceW":124,"sourceH":123},
"8":{"x":891,"y":336,"w":118,"h":116,"offX":0,"offY":0,"sourceW":118,"sourceH":116},
"7":{"x":765,"y":336,"w":124,"h":113,"offX":0,"offY":0,"sourceW":124,"sourceH":113},
"6":{"x":932,"y":0,"w":90,"h":113,"offX":0,"offY":0,"sourceW":90,"sourceH":113},
"5":{"x":225,"y":333,"w":123,"h":105,"offX":0,"offY":0,"sourceW":123,"sourceH":105},
"4":{"x":806,"y":210,"w":123,"h":124,"offX":0,"offY":0,"sourceW":123,"sourceH":124},
"3":{"x":644,"y":211,"w":119,"h":126,"offX":0,"offY":0,"sourceW":119,"sourceH":126},
"2":{"x":104,"y":333,"w":119,"h":114,"offX":0,"offY":0,"sourceW":119,"sourceH":114},
"1":{"x":225,"y":440,"w":119,"h":106,"offX":0,"offY":0,"sourceW":119,"sourceH":106},
"0":{"x":350,"y":333,"w":110,"h":116,"offX":0,"offY":0,"sourceW":110,"sourceH":116},
"spin_btn_LYD":{"x":261,"y":0,"w":259,"h":187,"offX":0,"offY":0,"sourceW":259,"sourceH":187},
"spin_btn":{"x":0,"y":0,"w":259,"h":187,"offX":0,"offY":0,"sourceW":259,"sourceH":187},
"reels_right":{"x":52,"y":189,"w":50,"h":800,"offX":0,"offY":0,"sourceW":50,"sourceH":800},
"reels_left":{"x":0,"y":189,"w":50,"h":800,"offX":0,"offY":0,"sourceW":50,"sourceH":800},
"Line Count":{"x":522,"y":0,"w":400,"h":83,"offX":0,"offY":0,"sourceW":400,"sourceH":83},
"jackpot_lock":{"x":104,"y":261,"w":538,"h":70,"offX":0,"offY":0,"sourceW":538,"sourceH":70},
"JackPot":{"x":104,"y":189,"w":538,"h":70,"offX":0,"offY":0,"sourceW":538,"sourceH":70}}}